{
  "82A Jack Ln, Leeds, Leeds, UK": {
    "lat": 53.7870356,
    "lng": -1.5502471
  },
  "48 Austhorpe Road, Crossgates, Leeds, LS15 8DX., Leeds, UK": {
    "lat": 53.8060364,
    "lng": -1.4506869
  },
  "114 Crossgates Road,  Leeds, LS15 7NL, Leeds, UK": {
    "lat": 53.8132303,
    "lng": -1.4535113
  },
  "Killingbeck Drive LS14 6UF, UK": {
    "lat": 53.8057024,
    "lng": -1.4786586
  },
  "42-44 Church St, Woodlesford, Leeds LS26 8RD, UK": {
    "lat": 53.757767,
    "lng": -1.4470351
  },
  "Pontefract Rd, Leeds LS10 1AX, UK": {
    "lat": 53.7655661,
    "lng": -1.4976656
  },
  "13 Marsh St, Rothwell, Leeds LS26 0AG, UK": {
    "lat": 53.7471097,
    "lng": -1.4779327
  },
  "97 Aberford Rd, Woodlesford, Leeds LS26 8LQ, UK": {
    "lat": 53.7528742,
    "lng": -1.446544
  },
  "Skelton Grange Road LS10 1RS, UK": {
    "lat": 53.7755868,
    "lng": -1.4989396
  },
  "Crossgates Shopping Centre LS15 8ET, UK": {
    "lat": 53.8062412,
    "lng": -1.4517909
  },
  "24 Church Side, Methley, Leeds LS26 9EE, UK": {
    "lat": 53.7348143,
    "lng": -1.4095714
  },
  "76 Aberford Rd, Oulton, Leeds LS26 8HP, UK": {
    "lat": 53.7517153,
    "lng": -1.4477686
  },
  "Church Lane, Swillington, Leeds LS26 8DY, UK": {
    "lat": 53.7688919,
    "lng": -1.4187511
  },
  "25A Marsh Street, Rothwell, Leeds LS26 0AG, UK": {
    "lat": 53.74749,
    "lng": -1.476945
  },
  "22 Royds Lane, Rothwell, Leeds LS26 0BE, UK": {
    "lat": 53.7474699,
    "lng": -1.4763672
  },
  "78 Osmondthorpe Lane, Leeds LS9 9EF, UK": {
    "lat": 53.7988268,
    "lng": -1.4986139
  },
  "Quarry Hill, Oulton, Leeds LS26 8SZ, UK": {
    "lat": 53.7526495,
    "lng": -1.4498523
  },
  "999 York Road, Seacroft, Leeds LS14 6NX, UK": {
    "lat": 53.820696,
    "lng": -1.4589581
  },
  "Colton Lane LS15 9HZ, UK": {
    "lat": 53.789699,
    "lng": -1.4301996
  },
  "Stile Hill Way, Colton, Leeds LS15 9JH, UK": {
    "lat": 53.7929111,
    "lng": -1.4319928
  },
  "Lidgett Ln, Garforth, Leeds LS25 1LJ, UK": {
    "lat": 53.7895203,
    "lng": -1.391431
  },
  "Car Park, Marsh St, Rothwell, Leeds, Leeds, UK": {
    "lat": 53.7475082,
    "lng": -1.4774535
  },
  "Unit 1, Fusion Court, Aberford Road, Garforth, LS25 2GH, Leeds, UK": {
    "lat": 53.7969607,
    "lng": -1.3759315
  },
  "2 Sagar Street, Castleford, WF10 1AF, Leeds, UK": {
    "lat": 53.727371,
    "lng": -1.3517842
  },
  "Colton Retail Park, 1 Stile Hill Way, Colton, Leeds LS15 9JA, UK": {
    "lat": 53.7927277,
    "lng": -1.4321913
  },
  "The Springs Thorpe Park View, Leeds LS15 8GH, UK": {
    "lat": 53.7987109,
    "lng": -1.4248817
  },
  "34, 36 Commercial St, Rothwell, Leeds LS26 0AW, UK": {
    "lat": 53.7484869,
    "lng": -1.4766977
  },
  "UNIT 3,THE SPRINGS RETAIL, THORPE PARK APPROACH, LEEDS LS15 8GG, UK": {
    "lat": 53.8015678,
    "lng": -1.4241885
  },
  "OULTON MEDICAL CENTRE, QUARRY HILL, OULTON, LEEDS LS26 8SZ, UK": {
    "lat": 53.7526495,
    "lng": -1.4498523
  },
  "Church View Surgery (2nd Floor), Station Road, Leeds LS15 8BZ, UK": {
    "lat": 53.8039219,
    "lng": -1.4515263
  },
  "Colton Mill Medical Centre, Stile Hill Way, Colton, Leeds LS15 9JH, UK": {
    "lat": 53.7929111,
    "lng": -1.4319928
  }
}